README.txt
setup.py
boois_return_result/__init__.py
boois_return_result/return_result.py
boois_return_result.egg-info/PKG-INFO
boois_return_result.egg-info/SOURCES.txt
boois_return_result.egg-info/dependency_links.txt
boois_return_result.egg-info/requires.txt
boois_return_result.egg-info/top_level.txt
boois_return_result.egg-info/zip-safe