Metadata-Version: 1.1
Name: boois-return-result
Version: 1.1.4
Summary: boois_return_result
Home-page: http://www.boois.cn/
Author: boois
Author-email: admin@boois.cn
License: MIT
Keywords: boois_return_result
Platform: UNKNOWN
Classifier: License :: OSI Approved :: MIT License
Classifier: Programming Language :: Python
Classifier: Intended Audience :: Developers
Classifier: Operating System :: OS Independent
